Metadata-Version: 2.1
Name: sowemail
Version: 0.0.2
Summary: SoWeMail library for Python 3
Home-page: https://github.com/sowemail/sowemail-python
Author: Fourat ZOUARI
Author-email: opensource@sowemail.com
License: MIT
Download-URL: https://github.com/sowemail/sowemail-python/tarball/0.0.2
Keywords: API,SOWEMAIL
Platform: UNKNOWN
Classifier: Programming Language :: Python :: 3
Classifier: Programming Language :: Python :: 3.6
Classifier: Programming Language :: Python :: 3.7
Classifier: Programming Language :: Python :: 3.8
Requires-Python: >=3.6.*
